odoo8_addon_stock_inventory_chatter-8.0.1.0.0.99.dev4-py3.8-nspkg.pth
odoo_addons/stock_inventory_chatter/README.rst
odoo_addons/stock_inventory_chatter/__init__.py
odoo_addons/stock_inventory_chatter/__openerp__.py
odoo_addons/stock_inventory_chatter/data/stock_data.xml
odoo_addons/stock_inventory_chatter/i18n/ar.po
odoo_addons/stock_inventory_chatter/i18n/bg.po
odoo_addons/stock_inventory_chatter/i18n/bs.po
odoo_addons/stock_inventory_chatter/i18n/ca.po
odoo_addons/stock_inventory_chatter/i18n/cs.po
odoo_addons/stock_inventory_chatter/i18n/da.po
odoo_addons/stock_inventory_chatter/i18n/de.po
odoo_addons/stock_inventory_chatter/i18n/el_GR.po
odoo_addons/stock_inventory_chatter/i18n/en_GB.po
odoo_addons/stock_inventory_chatter/i18n/es.po
odoo_addons/stock_inventory_chatter/i18n/es_AR.po
odoo_addons/stock_inventory_chatter/i18n/es_CL.po
odoo_addons/stock_inventory_chatter/i18n/es_CO.po
odoo_addons/stock_inventory_chatter/i18n/es_CR.po
odoo_addons/stock_inventory_chatter/i18n/es_DO.po
odoo_addons/stock_inventory_chatter/i18n/es_EC.po
odoo_addons/stock_inventory_chatter/i18n/es_ES.po
odoo_addons/stock_inventory_chatter/i18n/es_MX.po
odoo_addons/stock_inventory_chatter/i18n/es_PE.po
odoo_addons/stock_inventory_chatter/i18n/es_PY.po
odoo_addons/stock_inventory_chatter/i18n/es_VE.po
odoo_addons/stock_inventory_chatter/i18n/et.po
odoo_addons/stock_inventory_chatter/i18n/eu.po
odoo_addons/stock_inventory_chatter/i18n/fa.po
odoo_addons/stock_inventory_chatter/i18n/fi.po
odoo_addons/stock_inventory_chatter/i18n/fr.po
odoo_addons/stock_inventory_chatter/i18n/gl.po
odoo_addons/stock_inventory_chatter/i18n/he.po
odoo_addons/stock_inventory_chatter/i18n/hr.po
odoo_addons/stock_inventory_chatter/i18n/hr_HR.po
odoo_addons/stock_inventory_chatter/i18n/hu.po
odoo_addons/stock_inventory_chatter/i18n/id.po
odoo_addons/stock_inventory_chatter/i18n/it.po
odoo_addons/stock_inventory_chatter/i18n/ja.po
odoo_addons/stock_inventory_chatter/i18n/ko.po
odoo8_addon_stock_inventory_chatter-8.0.1.0.0.99.dev4.dist-info/METADATA
odoo8_addon_stock_inventory_chatter-8.0.1.0.0.99.dev4.dist-info/WHEEL
odoo8_addon_stock_inventory_chatter-8.0.1.0.0.99.dev4.dist-info/namespace_packages.txt
odoo8_addon_stock_inventory_chatter-8.0.1.0.0.99.dev4.dist-info/top_level.txt
odoo8_addon_stock_inventory_chatter-8.0.1.0.0.99.dev4.dist-info/RECORD
