Metadata-Version: 2.1
Name: odoo8-addon-stock-inventory-chatter
Version: 8.0.1.0.0.99.dev4
Summary: Log changes being done in Inventory Adjustments
Home-page: https://github.com/OCA/stock-logistics-warehouse
Author: Eficent, initOS GmbH, Odoo Community Association (OCA)
Author-email: support@odoo-community.org
License: AGPL-3
Platform: UNKNOWN
Classifier: Programming Language :: Python
Classifier: Framework :: Odoo
Classifier: License :: OSI Approved :: GNU Affero General Public License v3
Requires-Python: ~=2.7
Requires-Dist: odoo (<9.0a,>=8.0a)
